{
  "geoblacklight_version": "1.0",
  "dc_identifier_s": "f9241ac9-19d3-4fb1-8aed-0e2b366e3884",
  "dc_rights_s": "Public",
  "dc_title_s": "Monroe County Indiana",
  "dct_provenance_s": "Indiana University",
  "layer_slug_s": "f9241ac9-19d3-4fb1-8aed-0e2b366e3884",
  "solr_geom": "ENVELOPE(-86.68,-86.31,39.35,39)",
  "solr_year_i": "1950",
  "dc_creator_sm": [
    "Stapleton,  John T., cartographer."
  ],
  "dc_description_s": "Blue line print.; Cadastral map showing landowners.; 1950. Scale approximately 1:63,360",
  "dc_format_s": "JPEG",
  "dct_references_s": "{\"http://schema.org/downloadUrl\":\"https://purl.dlib.indiana.edu/iudl/images/VAC3073/full/VAC3073-M-00331\",\"http://schema.org/url\":\"http://purl.dlib.indiana.edu/iudl/images/VAC3073/VAC3073-M-00331\"}",
  "dct_spatial_sm": [
    "Indiana",
    "Monroe County, Indiana"
  ],
  "layer_modified_dt": "2022-04-01T15:23:27Z",
  "dc_language_sm": [
    "eng"
  ],
  "dct_temporal_sm": [
    "1950"
  ]
}