{
  "dct_title_s": "Steuben County, Indiana",
  "dct_description_sm": [
    "Includes text. Scale approximately 1:150,000."
  ],
  "dct_language_sm": [
    "eng"
  ],
  "dct_creator_sm": [
    "Rakestraw,  O. F., cartographer."
  ],
  "dct_publisher_sm": [
    "O.F. Rakestraw?"
  ],
  "schema_provider_s": "Indiana University",
  "gbl_resourceClass_sm": [
    "Maps"
  ],
  "dcat_keyword_sm": [
    "Indiana Historic Maps"
  ],
  "dct_temporal_sm": [
    "1899"
  ],
  "gbl_indexYear_im": [
    "1899"
  ],
  "gbl_dateRange_drsim": [
    "[1899 TO 1899]"
  ],
  "dct_spatial_sm": [
    "Steuben County, Indiana",
    "Indiana"
  ],
  "locn_geometry": "ENVELOPE(-85.1801,-84.8,41.7501,41.51)",
  "dcat_bbox": "ENVELOPE(-85.1801,-84.8,41.7501,41.51)",
  "dcat_centroid": "41.63005,-84.99005",
  "pcdm_memberOf_sm": [
    "64bd8c4c-8e60-4956-b43d-bdc3f93db488"
  ],
  "dct_isPartOf_sm": [
    "01d-01"
  ],
  "dct_accessRights_s": "Public",
  "dct_format_s": "JPEG",
  "dct_references_s": "{\"http://schema.org/downloadUrl\":\"https://purl.dlib.indiana.edu/iudl/images/VAC3073/full/VAC3073-M-00011\",\"http://schema.org/url\":\"http://purl.dlib.indiana.edu/iudl/images/VAC3073/VAC3073-M-00011\"}",
  "id": "642fbb9a-cf98-4723-bb4f-439a17353739",
  "dct_identifier_sm": [
    "642fbb9a-cf98-4723-bb4f-439a17353739"
  ],
  "gbl_mdModified_dt": "2022-04-01T15:33:52Z",
  "gbl_mdVersion_s": "Aardvark"
}