{
  "dct_title_s": "Map of Marion County Indiana",
  "dct_description_sm": [
    "Cadastral map showing landowners.; Originally printed in 2 sheets. Scale approximately 1:32,500"
  ],
  "dct_language_sm": [
    "eng"
  ],
  "dct_publisher_sm": [
    "Condit, Wright & Hayden?"
  ],
  "schema_provider_s": "Indiana University",
  "gbl_resourceClass_sm": [
    "Maps"
  ],
  "gbl_resourceType_sm": [
    "Cadastral maps"
  ],
  "dcat_keyword_sm": [
    "Cadastral",
    "Landowners",
    "Land ownership",
    "Real property"
  ],
  "dct_temporal_sm": [
    "1855"
  ],
  "gbl_indexYear_im": [
    "1855"
  ],
  "gbl_dateRange_drsim": [
    "[1855 TO 1855]"
  ],
  "dct_spatial_sm": [
    "Indiana",
    "Indiana--Marion County"
  ],
  "locn_geometry": "POLYGON((-86.33 39.93, -85.95 39.93, -85.95 39.63, -86.33 39.63, -86.33 39.93))",
  "dcat_bbox": "ENVELOPE(-86.33,-85.95,39.93,39.63)",
  "dcat_centroid": "39.78,-86.14",
  "pcdm_memberOf_sm": [
    "64bd8c4c-8e60-4956-b43d-bdc3f93db488"
  ],
  "dct_accessRights_s": "Public",
  "dct_format_s": "JPEG",
  "dct_references_s": "{\"http://schema.org/url\":\"http://purl.dlib.indiana.edu/iudl/images/VAC3073/VAC3073-M-00149\",\"http://schema.org/downloadUrl\":[{\"url\":\"https://purl.dlib.indiana.edu/iudl/images/VAC3073/full/VAC3073-M-00149\",\"label\":\"JPEG\"}]}",
  "id": "93185c98-c28c-452b-8000-4538bfea9f13",
  "dct_identifier_sm": [
    "93185c98-c28c-452b-8000-4538bfea9f13"
  ],
  "gbl_mdVersion_s": "Aardvark"
}