{
  "dct_title_s": "Franklin Co., Ind.",
  "dct_description_sm": [
    "Scale approximately 1:60,000."
  ],
  "dct_language_sm": [
    "eng"
  ],
  "dct_publisher_sm": [
    "Scarborough Co."
  ],
  "schema_provider_s": "Indiana University",
  "gbl_resourceClass_sm": [
    "Maps"
  ],
  "dct_temporal_sm": [
    "1908"
  ],
  "gbl_indexYear_im": [
    "1908"
  ],
  "gbl_dateRange_drsim": [
    "[1908 TO 1908]"
  ],
  "dct_spatial_sm": [
    "Indiana",
    "Indiana--Franklin County"
  ],
  "locn_geometry": "POLYGON((-85.280 39.510, -84.800 39.510, -84.800 39.260, -85.280 39.260, -85.280 39.510))",
  "dcat_bbox": "ENVELOPE(-85.280,-84.800,39.510,39.260)",
  "dcat_centroid": "39.385,-85.03999999999999",
  "pcdm_memberOf_sm": [
    "64bd8c4c-8e60-4956-b43d-bdc3f93db488"
  ],
  "dct_accessRights_s": "Public",
  "dct_format_s": "JPEG",
  "dct_references_s": "{\"http://schema.org/url\":\"http://purl.dlib.indiana.edu/iudl/images/VAC3073/VAC3073-M-00278\",\"http://schema.org/downloadUrl\":[{\"url\":\"https://purl.dlib.indiana.edu/iudl/images/VAC3073/full/VAC3073-M-00278\",\"label\":\"JPEG\"}]}",
  "id": "a391258c-454e-4420-90d9-22b9ee3bfe80",
  "dct_identifier_sm": [
    "a391258c-454e-4420-90d9-22b9ee3bfe80"
  ],
  "gbl_mdVersion_s": "Aardvark"
}