{
  "dct_title_s": "Owen County: T. 9 N., Rs.  5 and 6 W. [Jefferson Twp, Coal City]",
  "dct_language_sm": [
    "eng"
  ],
  "schema_provider_s": "Indiana University",
  "gbl_resourceClass_sm": [
    "Maps"
  ],
  "gbl_resourceType_sm": [
    "Geological maps",
    "Geological cross-sections"
  ],
  "dct_subject_sm": [
    "",
    "Coal",
    "Geology, Stratigraphic"
  ],
  "dct_temporal_sm": [
    "1898"
  ],
  "dct_issued_s": "1898",
  "gbl_indexYear_im": [
    "1898"
  ],
  "gbl_dateRange_drsim": [
    "[1898 TO 1898]"
  ],
  "dct_spatial_sm": [
    "Indiana--Owen County",
    "Indiana"
  ],
  "locn_geometry": "POLYGON((-87.100 39.500, -86.600 39.500, -86.600 39.200, -87.100 39.200, -87.100 39.500))",
  "dcat_bbox": "ENVELOPE(-87.100,-86.600,39.500,39.200)",
  "dcat_centroid": "39.35,-86.85",
  "pcdm_memberOf_sm": [
    "64bd8c4c-8e60-4956-b43d-bdc3f93db488"
  ],
  "dct_isPartOf_sm": [
    "01d-01"
  ],
  "dct_accessRights_s": "Public",
  "dct_format_s": "JPEG",
  "gbl_wxsIdentifier_s": "4t64hq95f",
  "dct_references_s": "{\"http://schema.org/url\":\"https://purl.dlib.indiana.edu/iudl/images/VAC3073/VAC3073-M-01454\",\"http://iiif.io/api/presentation#manifest\":\"https://digitalcollections.iu.edu/concern/images/4t64hq95f/manifest\"}",
  "id": "VAC3073-M-01454",
  "gbl_mdVersion_s": "Aardvark"
}