{
  "dct_title_s": "Soil map of Clark and a portion of Floyd Counties",
  "dct_description_sm": [
    "Detached from: A soil survey of Clark, Floyd, and Harrison counties / Robert W. Ellis. In Indiana Department of Geology and Natural Resources thirty-second annual report ... 1907. Indianapolis : Wm. B. Burford, 1908. Page 245.",
    "Imprint: [Indianapolis] : [Indiana Department of Geology and Natural Resources], [1908]",
    "Dimensions: 49 x 64 cm; Scale: Approximately 1:90,000",
    "Coordinates: W0855940 W0852455 N0383624 N0381601"
  ],
  "dct_language_sm": [
    "eng"
  ],
  "dct_creator_sm": [
    "Ellis, R. W. (Robert W.)"
  ],
  "dct_publisher_sm": [
    "Indiana. Department of Geology and Natural Resources"
  ],
  "schema_provider_s": "Indiana University",
  "gbl_resourceClass_sm": [
    "Maps"
  ],
  "gbl_resourceType_sm": [
    "Thematic maps"
  ],
  "dct_subject_sm": [
    "Soils"
  ],
  "dct_temporal_sm": [
    "1907"
  ],
  "dct_issued_s": "1908",
  "gbl_indexYear_im": [
    "1907"
  ],
  "gbl_dateRange_drsim": [
    "[1907 TO 1907]"
  ],
  "dct_spatial_sm": [
    "Indiana--Floyd County",
    "Indiana",
    "Indiana--Clark County"
  ],
  "locn_geometry": "POLYGON((-85.980 38.600, -85.400 38.600, -85.400 38.260, -85.980 38.260, -85.980 38.600))",
  "dcat_bbox": "ENVELOPE(-85.980,-85.400,38.600,38.260)",
  "dcat_centroid": "38.43,-85.69",
  "pcdm_memberOf_sm": [
    "64bd8c4c-8e60-4956-b43d-bdc3f93db488"
  ],
  "dct_isPartOf_sm": [
    "01d-01"
  ],
  "dct_accessRights_s": "Public",
  "dct_format_s": "JPEG",
  "gbl_wxsIdentifier_s": "vt151n062",
  "dct_references_s": "{\"http://schema.org/url\":\"https://purl.dlib.indiana.edu/iudl/images/VAC3073/VAC3073-M-00249\",\"http://iiif.io/api/presentation#manifest\":\"https://digitalcollections.iu.edu/concern/images/vt151n062/manifest\"}",
  "id": "VAC3073-M-00249",
  "dct_identifier_sm": [
    "VAC3073-M-00249",
    "G4093.C4J3 1907 .E4"
  ],
  "gbl_mdVersion_s": "Aardvark"
}