{
  "dct_title_s": "Land in farms, 1964, in percent",
  "dct_description_sm": [
    "Includes ancillary map Types of farming. Computer generated isopleth map obtained through use of the facilities of Indiana University's Research Computer Center. Detached from: An atlas of Indiana / by Robert C. Kingsbury , with contributions from John M. Hollingsworth and others. Bloomington, Indiana : Department of Geography, Indiana University, [1970]. Page 60.",
    "Imprint: Bloomington, Indiana : Department of Geography, Indiana University, [1970]",
    "Dimensions: 23 x 18 cm; Scale: Approximately 1:2,700,000"
  ],
  "dct_language_sm": [
    "eng"
  ],
  "dct_creator_sm": [
    "Indiana University. Research Computing Center; Kingsbury, Robert C."
  ],
  "dct_publisher_sm": [
    "Indiana University. Department of Geography"
  ],
  "schema_provider_s": "Indiana University",
  "gbl_resourceClass_sm": [
    "Maps"
  ],
  "gbl_resourceType_sm": [
    "Thematic maps"
  ],
  "dct_subject_sm": [
    "Agricultural systems",
    "Farms",
    "Agricultural resources"
  ],
  "dct_temporal_sm": [
    "1970"
  ],
  "dct_issued_s": "1970",
  "gbl_indexYear_im": [
    "1970"
  ],
  "gbl_dateRange_drsim": [
    "[1970 TO 1970]"
  ],
  "dct_spatial_sm": [
    "Indiana"
  ],
  "locn_geometry": "POLYGON((-88.100 41.800, -84.800 41.800, -84.800 37.800, -88.100 37.800, -88.100 41.800))",
  "dcat_bbox": "ENVELOPE(-88.100,-84.800,41.800,37.800)",
  "dcat_centroid": "39.8,-86.44999999999999",
  "pcdm_memberOf_sm": [
    "64bd8c4c-8e60-4956-b43d-bdc3f93db488"
  ],
  "dct_isPartOf_sm": [
    "01d-01"
  ],
  "dct_accessRights_s": "Public",
  "dct_format_s": "JPEG",
  "gbl_wxsIdentifier_s": "j96032869",
  "dct_references_s": "{\"http://schema.org/url\":\"https://purl.dlib.indiana.edu/iudl/images/VAC3073/VAC3073-M-00576\",\"http://iiif.io/api/presentation#manifest\":\"https://digitalcollections.iu.edu/concern/images/j96032869/manifest\"}",
  "id": "VAC3073-M-00576",
  "dct_identifier_sm": [
    "G4091.J1 1964 .K58"
  ],
  "gbl_mdVersion_s": "Aardvark"
}