{
  "dct_title_s": "Ohio County [Indiana] preliminary land use map",
  "dct_description_sm": [
    "Includes chart showing type of land use, acreage, and recommended use.",
    "Imprint: [Rising Sun, Ind.?] : The Committee, [1940?]",
    "Dimensions: 11 x 19 cm, on sheet 39 x 28 cm; Scale: Scale not given.",
    "Coordinates: W0850825 W0844947 N0390151 N0385403"
  ],
  "dct_language_sm": [
    "eng"
  ],
  "dct_creator_sm": [
    "Ohio County (Ind.). Land Use Planning Committtee"
  ],
  "dct_publisher_sm": [
    "Ohio County (Ind.). Land Use Planning Committtee"
  ],
  "schema_provider_s": "Indiana University",
  "gbl_resourceClass_sm": [
    "Maps"
  ],
  "gbl_resourceType_sm": [
    "Thematic maps"
  ],
  "dct_subject_sm": [
    "Land use"
  ],
  "dct_temporal_sm": [
    "1940?"
  ],
  "dct_issued_s": "1940",
  "gbl_indexYear_im": [
    "1940"
  ],
  "gbl_dateRange_drsim": [
    "[1940 TO 1940]"
  ],
  "dct_spatial_sm": [
    "Indiana--Ohio County",
    "Indiana"
  ],
  "locn_geometry": "POLYGON((-85.130 39.010, -84.810 39.010, -84.810 38.900, -85.130 38.900, -85.130 39.010))",
  "dcat_bbox": "ENVELOPE(-85.130,-84.810,39.010,38.900)",
  "dcat_centroid": "38.955,-84.97",
  "pcdm_memberOf_sm": [
    "64bd8c4c-8e60-4956-b43d-bdc3f93db488"
  ],
  "dct_isPartOf_sm": [
    "01d-01"
  ],
  "dct_accessRights_s": "Public",
  "dct_format_s": "JPEG",
  "gbl_wxsIdentifier_s": "qv33t015x",
  "dct_references_s": "{\"http://schema.org/url\":\"https://purl.dlib.indiana.edu/iudl/images/VAC3073/VAC3073-M-00155\",\"http://iiif.io/api/presentation#manifest\":\"https://digitalcollections.iu.edu/concern/images/qv33t015x/manifest\"}",
  "id": "VAC3073-M-00155",
  "dct_identifier_sm": [
    "5834b4cc-a1d8-46ae-974e-83996619edb3",
    "G4093.O3 1940 .O45"
  ],
  "gbl_mdVersion_s": "Aardvark"
}