{
  "geoblacklight_version": "1.0",
  "dc_identifier_s": "http://purl.dlib.indiana.edu/iudl/images/VAC9619/VAC9619-001096|G7000 s50 .S68 М-36-116-Б",
  "dc_rights_s": "Public",
  "dc_title_s": "М-36-116-Б Дериевка (Deriyivka, Ukraine)",
  "dct_provenance_s": "Indiana University",
  "layer_slug_s": "VAC9619-001096",
  "solr_geom": "ENVELOPE(34,33.75,49,48.833)",
  "solr_year_i": "1931",
  "dc_description_s": "Modern area represented: Deriyivka, Kirovohrad oblast, Ukraine; Scale =1:50,000; Не подлежит оглашению",
  "dc_format_s": "GeoTIFF",
  "dct_references_s": "{\"http://lccn.loc.gov/sh85035852\":\"https://iucat.iu.edu/catalog/5020131\",\"http://schema.org/url\":\"http://purl.dlib.indiana.edu/iudl/images/VAC9619/VAC9619-001096\"}",
  "dct_spatial_sm": [
    "Ukraine--Deriyivka",
    "Ukraine"
  ],
  "layer_modified_dt": "2023-05-09T06:04:41Z",
  "dc_language_sm": [
    "rus"
  ],
  "dc_publisher_s": "Управление военных топографов",
  "dct_issued_s": "1931",
  "dct_temporal_sm": [
    "1931-1932"
  ]
}