{
  "geoblacklight_version": "1.0",
  "dc_identifier_s": "2cd95dea-4162-444c-b6dc-69c9d92e0f46",
  "dc_rights_s": "Public",
  "dc_title_s": "Cram's township map of Indiana: showing counties, political and congressional townships, base lines, and meridians, all cities, villages, with unabridged index, 3,500 name places, latest federal census",
  "dct_provenance_s": "Indiana University",
  "layer_slug_s": "2cd95dea-4162-444c-b6dc-69c9d92e0f46",
  "solr_geom": "ENVELOPE(-88.11,-84.75,41.75,37.86)",
  "solr_year_i": "1945",
  "dc_description_s": "LR941.; Includes index, description of the township and range and land survey systems, population tables, and inset of Trunk highway. Scale approximately 1:443,520. 7 miles to 1 inch.",
  "dc_format_s": "JPEG",
  "dct_references_s": "{\"http://schema.org/downloadUrl\":\"https://purl.dlib.indiana.edu/iudl/images/VAC3073/full/VAC3073-M-00104\",\"http://schema.org/url\":\"http://purl.dlib.indiana.edu/iudl/images/VAC3073/VAC3073-M-00104\"}",
  "dct_spatial_sm": [
    "Indiana"
  ],
  "layer_modified_dt": "2023-02-03T21:11:33Z",
  "dc_language_sm": [
    "eng"
  ],
  "dc_publisher_s": "George F. Cram Co.",
  "dct_temporal_sm": [
    "1945"
  ]
}