{
  "geoblacklight_version": "1.0",
  "dc_identifier_s": "http://purl.dlib.indiana.edu/iudl/images/VAC9619/VAC9619-000641|G7000 s50 .S68 sheet N-35-90-B",
  "dc_rights_s": "Public",
  "dc_title_s": "N-35-90-Б Слобода (Slabada, Belarus)",
  "dct_provenance_s": "Indiana University",
  "layer_slug_s": "VAC9619-000641",
  "solr_geom": "ENVELOPE(27,26.75,53.667,53.5)",
  "solr_year_i": "1908",
  "dc_description_s": "Modern area represented: Slabada (Slabada), Minsk Oblast, Belarus; Scale =1:50,000; Не подлежит оглашению",
  "dc_format_s": "GeoTIFF",
  "dct_references_s": "{\"http://schema.org/url\":\"http://purl.dlib.indiana.edu/iudl/images/VAC9619/VAC9619-000641\",\"http://schema.org/downloadUrl\":\"https://drive.google.com/open?id=1yvhxZ36MOk-sOh0q-bYrOEGycfvIlTsl\",\"http://lccn.loc.gov/sh85035852\":\"https://iucat.iu.edu/catalog/5020131\"}",
  "dct_spatial_sm": [
    "Slabada, Belarus",
    "Belarus"
  ],
  "layer_modified_dt": "2022-07-06T01:37:40Z",
  "dc_language_sm": [
    "rus"
  ],
  "dc_publisher_s": "Управление военных топографов РККА",
  "dct_issued_s": "1908",
  "dct_temporal_sm": [
    "1908-1936"
  ]
}