{
  "geoblacklight_version": "1.0",
  "dc_identifier_s": "VAC9619-001092",
  "dc_rights_s": "Public",
  "dc_title_s": "М-36-115-А Золотаревка (Zolotarivka, Ukraine)",
  "dct_provenance_s": "Indiana University",
  "layer_slug_s": "VAC9619-001092",
  "solr_geom": "ENVELOPE(33.25,33,49,48.833)",
  "solr_year_i": "1931",
  "dc_description_s": "Modern area represented: Zolotarivka, Kirovohrad oblast, Ukraine; Scale =1:50,000; Не подлежит оглашению",
  "dc_format_s": "GeoTIFF",
  "dct_references_s": "{\"http://lccn.loc.gov/sh85035852\":\"https://iucat.iu.edu/catalog/5020131\",\"http://schema.org/downloadUrl\":\"https://iu.box.com/s/2km68q76371hyxb6gzvzf1x2d940gfbe\",\"http://schema.org/url\":\"http://purl.dlib.indiana.edu/iudl/images/VAC9619/VAC9619-001092\"}",
  "dct_spatial_sm": [
    "Zolotarivka, Ukraine",
    "Ukraine"
  ],
  "layer_modified_dt": "2022-04-01T15:25:20Z",
  "dc_language_sm": [
    "rus"
  ],
  "dc_publisher_s": "Управление военных топографов РККА",
  "dct_issued_s": "1931",
  "dct_temporal_sm": [
    "1931"
  ]
}