{
  "geoblacklight_version": "1.0",
  "dc_identifier_s": "VAC9619-000365",
  "dc_rights_s": "Public",
  "dc_title_s": "N-34-91-А Швентайнен (Świętajno, Poland)",
  "dct_provenance_s": "Indiana University",
  "layer_slug_s": "VAC9619-000365",
  "solr_geom": "ENVELOPE(21.25,21,53.6667,53.5)",
  "solr_year_i": "1914",
  "dc_description_s": "Modern area represented: Świętajno, Poland; Scale =1:50,000; Captured map",
  "dc_format_s": "GeoTIFF",
  "dct_references_s": "{\"http://lccn.loc.gov/sh85035852\":\"https://iucat.iu.edu/catalog/5020131\",\"http://schema.org/downloadUrl\":\"https://iu.box.com/s/o6n7rlnmsioo8lyzglhgu4k0uqftxxu7\",\"http://schema.org/url\":\"http://purl.dlib.indiana.edu/iudl/images/VAC9619/VAC9619-000365\"}",
  "dct_spatial_sm": [
    "Świętajno, Poland",
    "Poland"
  ],
  "layer_modified_dt": "2022-04-01T15:33:30Z",
  "dc_language_sm": [
    "rus"
  ],
  "dc_publisher_s": "Генеральный штаб Красной Армии",
  "dct_issued_s": "1914",
  "dct_temporal_sm": [
    "1914-1941"
  ]
}