{
  "geoblacklight_version": "1.0",
  "dc_identifier_s": "VAC9619-003624",
  "dc_rights_s": "Public",
  "dc_title_s": "N-34-34-Г-г Гелгудышки (Gelgaudiškis, Lithuania)",
  "dct_provenance_s": "Indiana University",
  "layer_slug_s": "VAC9619-003624",
  "solr_geom": "ENVELOPE(23,22.875,55.083,55)",
  "solr_year_i": "1892",
  "dc_description_s": "Modern area represented: Gelgaudiškis, Lithuania; Scale =1:25,000; Секретно",
  "dc_format_s": "GeoTIFF",
  "dct_references_s": "{\"http://lccn.loc.gov/sh85035852\":\"https://iucat.iu.edu/catalog/14701157\",\"http://schema.org/downloadUrl\":\"https://iu.box.com/s/4jooe4w5fnp4ze4kb2darx6gh8twlht2\",\"http://schema.org/url\":\"http://purl.dlib.indiana.edu/iudl/images/VAC9619/VAC9619-003624\"}",
  "dct_spatial_sm": [
    "Gelgaudiškis, Lithuania",
    "Lithuania"
  ],
  "layer_modified_dt": "2022-04-01T15:27:33Z",
  "dc_language_sm": [
    "rus"
  ],
  "dc_publisher_s": "Генеральный штаб Красной Армии",
  "dct_issued_s": "1892",
  "dct_temporal_sm": [
    "1892-1941"
  ]
}