{
  "geoblacklight_version": "1.0",
  "dc_identifier_s": "VAC9619-002758",
  "dc_rights_s": "Public",
  "dc_title_s": "M-34-22 Любартов (Lubartów, Poland)",
  "dct_provenance_s": "Indiana University",
  "layer_slug_s": "VAC9619-002758",
  "solr_geom": "ENVELOPE(23,22.5,51.667,51.333)",
  "solr_year_i": "1880",
  "dc_description_s": "Modern area represented: Lubartów, Lublin province, Poland; Scale =1:100,000",
  "dc_format_s": "GeoTIFF",
  "dct_references_s": "{\"http://lccn.loc.gov/sh85035852\":\"https://iucat.iu.edu/catalog/5020129\",\"http://schema.org/downloadUrl\":\"https://iu.box.com/s/bd6v1ma80yotltwhy7svxlaer8yee7jc\",\"http://schema.org/url\":\"http://purl.dlib.indiana.edu/iudl/images/VAC9619/VAC9619-002758\"}",
  "dct_spatial_sm": [
    "Lubartów, Poland",
    "Poland"
  ],
  "layer_modified_dt": "2022-04-01T15:27:21Z",
  "dc_language_sm": [
    "rus"
  ],
  "dc_publisher_s": "Генеральный штаб РККА",
  "dct_issued_s": "1880",
  "dct_temporal_sm": [
    "1880-1914"
  ]
}